settle/__init__.py
settle/version.py
settle-0.0.1.dist-info/licenses/LICENSE
settle-0.0.1.dist-info/METADATA
settle-0.0.1.dist-info/WHEEL
settle-0.0.1.dist-info/top_level.txt
settle-0.0.1.dist-info/RECORD
