Metadata-Version: 2.4
Name: settle
Version: 0.0.1
Summary: An open-source reconciliation and matching kernel for financial systems.
Author-email: Joseph Marks <joe@finorchestrate.com>
License: MIT
Project-URL: Homepage, https://praescious.ai
Project-URL: Repository, https://github.com/finorchestrate/settle
Keywords: accounting,reconciliation,finance,matching,ledger
Classifier: Development Status :: 2 - Pre-Alpha
Classifier: Intended Audience :: Financial and Insurance Industry
Classifier: License :: OSI Approved :: MIT License
Classifier: Programming Language :: Python :: 3
Requires-Python: >=3.9
License-File: LICENSE
Dynamic: license-file
